README.rst
setup.py
pybrowsertest/__init__.py
pybrowsertest/widgets.py
pybrowsertest.egg-info/PKG-INFO
pybrowsertest.egg-info/SOURCES.txt
pybrowsertest.egg-info/dependency_links.txt
pybrowsertest.egg-info/requires.txt
pybrowsertest.egg-info/top_level.txt
test/tests.py