Metadata-Version: 1.1
Name: pybrowsertest
Version: 0.0.4
Summary: Facility to use Selenium
Home-page: https://github.com/magmax/pybrowsertest
Author: Miguel Ángel García
Author-email: <miguelangel.garcia@tuenti.com>
License: LGPL
Platform: UNKNOWN
Classifier: Development Status :: 4 - Beta
Classifier: Topic :: Software Development :: Testing
Classifier: License :: OSI Approved :: GNU Lesser General Public License v3 or later (LGPLv3+)
Classifier: Environment :: Console
Classifier: Intended Audience :: Developers
Classifier: Topic :: Software Development :: User Interfaces
Classifier: Topic :: Software Development :: Libraries :: Application Frameworks
